cdk_vpc_pattern/__init__.py
cdk_vpc_pattern/py.typed
cdk_vpc_pattern/_jsii/__init__.py
cdk_vpc_pattern/_jsii/cdk-vpc-pattern@0.0.4.jsii.tgz
cdk_vpc_pattern-0.0.4.dist-info/LICENSE
cdk_vpc_pattern-0.0.4.dist-info/METADATA
cdk_vpc_pattern-0.0.4.dist-info/WHEEL
cdk_vpc_pattern-0.0.4.dist-info/top_level.txt
cdk_vpc_pattern-0.0.4.dist-info/RECORD
